docs/Makefile
docs/changelog.rst
docs/codelist.csv
docs/conf.py
docs/index.rst
docs/requirements.txt
docs/schema.json
sphinxcontrib/opencontracting.py
sphinxcontrib_opencontracting-0.0.10.dist-info/LICENSE
sphinxcontrib_opencontracting-0.0.10.dist-info/METADATA
sphinxcontrib_opencontracting-0.0.10.dist-info/WHEEL
sphinxcontrib_opencontracting-0.0.10.dist-info/top_level.txt
sphinxcontrib_opencontracting-0.0.10.dist-info/RECORD
