Metadata-Version: 2.1
Name: sphinxcontrib-opencontracting
Version: 0.0.10
Summary: Provides Sphinx directives for the documentation of the Open Contracting Data Standard
Author-email: Open Contracting Partnership <data@open-contracting.org>
License: BSD
Project-URL: Homepage, https://github.com/open-contracting/sphinxcontrib-opencontracting
Classifier: License :: OSI Approved :: BSD License
Classifier: Operating System :: OS Independent
Classifier: Programming Language :: Python :: 3.8
Classifier: Programming Language :: Python :: 3.9
Classifier: Programming Language :: Python :: 3.10
Classifier: Programming Language :: Python :: 3.11
Classifier: Programming Language :: Python :: 3.12
Classifier: Programming Language :: Python :: Implementation :: CPython
Classifier: Programming Language :: Python :: Implementation :: PyPy
Classifier: Framework :: Sphinx :: Extension
License-File: LICENSE
Requires-Dist: docutils
Requires-Dist: jsonpointer
Requires-Dist: MyST-Parser
Requires-Dist: requests
Requires-Dist: ocdsextensionregistry >=0.0.8
Requires-Dist: sphinx
Provides-Extra: test
Requires-Dist: coverage ; extra == 'test'
Requires-Dist: lxml ; extra == 'test'
Requires-Dist: pytest ; extra == 'test'
Requires-Dist: sphinx >=4.4.0 ; extra == 'test'
